dual_numbers/__init__.py
dual_numbers-0.0.11.dist-info/LICENSE
dual_numbers-0.0.11.dist-info/METADATA
dual_numbers-0.0.11.dist-info/WHEEL
dual_numbers-0.0.11.dist-info/top_level.txt
dual_numbers-0.0.11.dist-info/RECORD
