Metadata-Version: 2.1
Name: dual_numbers
Version: 0.0.11
Summary: 2D dual numbers for python, with support for complex scalars or arbitrary domains
Author-email: Vicente Carrasco Álvarez <vidacaal@gmail.com>
Project-URL: Homepage, https://github.com/vichoca9/dual_numbers
Project-URL: Issues, https://github.com/vichoca9/dual_numbers/issues
Classifier: Programming Language :: Python :: 3
Classifier: License :: OSI Approved :: MIT License
Classifier: Operating System :: OS Independent
Requires-Python: >=3.7
License-File: LICENSE
Requires-Dist: forbiddenfruit
Requires-Dist: custom-literals
